{
    "version": "v1.0.0",
    "locale": {
        "locales": [
            "en",
            "ar"
        ],
        "override": {
            "en": {
                "infosAdmins": {
                    "admin1": "Governorate",
                    "admin2": "District",
                    "admin3": "Sub district"
                }
            },
            "ar": {
                "infosAdmins": {
                    "admin1": "محافظة",
                    "admin2": "يصرف",
                    "admin3": "العزلة"
                }
            }
        }
    },
    "textContent": {
        "name": {
            "en": "Lebanon",
            "ar": "لبنان"
        },
        "opsmapDescr": {
            "en": "Emergency RNA Plus - Site Management",
            "ar": "إدارة موقع إمرجنسي آر إن إيه بلس"
        }
    },
    "iframe": {
        "url": "",
        "display": false
    },
    "footerLogos": [
        {
            "title": {
                "en": "Webdev",
                "ar": "ويبديف"
            },
            "logos": [
                {
                    "name": "CartONG",
                    "urlLogo": "Logo/CartONG_logo_long_0_0_0.png",
                    "urlRedirection": "https://www.cartong.org"
                }
            ]
        },
        {
            "title": {
                "en": "Sector Lead",
                "ar": "قيادة القطاع"
            },
            "logos": [
                {
                    "name": "CCCM cluster in Lebanon",
                    "urlLogo": "Logo/cccm.png",
                    "urlRedirection": "https://www.cccmcluster.org/where-we-work/lebanon"
                },
                {
                    "name": "ACTED",
                    "urlLogo": "Logo/acted.png",
                    "urlRedirection": "https://www.acted.org/en/"
                },

                {
                    "name": "REACH Initiative",
                    "urlLogo": "Logo/reach.png",
                    "urlRedirection": "https://www.reach-initiative.org/"
                },
                {
                    "name": "UNHCR",
                    "urlLogo": "Logo/unhcr.png",
                    "urlRedirection": "https://www.unhcr.org/ua"
                }
            ]
        },
        {
            "title": {
                "en": "Fieldwork",
                "ar": "العمل الميداني"
            },
            "logos": [
                {
                    "name": "CCCM cluster in Lebanon",
                    "urlLogo": "Logo/cccm.png",
                    "urlRedirection": "https://www.cccmcluster.org/where-we-work/lebanon"
                }
            ]
        },
        {
            "title": {
                "en": "Coordination and IM support",
                "ar": "التنسيق ودعم الرسائل الفورية"
            },
            "logos": [
                {
                    "name": "CCCM cluster in Lebanon",
                    "urlLogo": "Logo/cccm.png",
                    "urlRedirection": "https://www.cccmcluster.org/where-we-work/lebanon"
                },
                {
                    "name": "Impact Initiatives",
                    "urlLogo": "Logo/impact.png",
                    "urlRedirection": "https://www.impact-initiatives.org"
                }
            ]
        }
    ],
    "spatial": {
        "mapConfig": {
            "bounds": [
                32.58,
                33.32,
                38.25,
                34.45
            ]
        },
        "dbConfig": {
            "admin1": "adm1_source_code",
            "admin2": "adm2_source_code",
            "admin3": "adm3_source_code"
        },
        "adminLevels": [
            "admin1",
            "admin2",
            "admin3"
        ],
        "adminLevelsMap": [
            "admin1",
            "admin2"
        ]
    },
    "surveys": [
        {
            "type": "gsheet",
            "name": "Round 1",
            "fdf": {
                "folder": "FDF_R1",
                "fdfId": "LEBANON_1"
            },
            "name": "CCCM Yemen - Site Reporting Tool (SMT)",
            "submissionsUrl": "https://docs.google.com/spreadsheets/d/e/2PACX-1vQ2DKV-aqg-9SZMBBtg7A3bWShMdZPLoT5HLOQY_bjpREMa4cC91YAu-DWsMDNdo5rm71G2uh7b8DBl/pub?gid=0&single=true&output=csv",
            "submissionsTrUrl": "https://docs.google.com/spreadsheets/d/e/2PACX-1vQ2DKV-aqg-9SZMBBtg7A3bWShMdZPLoT5HLOQY_bjpREMa4cC91YAu-DWsMDNdo5rm71G2uh7b8DBl/pub?gid=845458241&single=true&output=csv",
            "options": {
                "anonymousMode": "text",
                "siteZoomMode": "admin"
            },
            "additionalFiltersDescription": [
                {
                    "field": "smc_agency",
                    "name": {
                        "en": "Organization",
                        "ar": "وكالة تنسيق وإدارة الموقع (SMC)"
                    }
                }
            ],
            "spatial": {
                "siteFields": {
                    "id": "site",
                    "lastUpdate": "reporting_month",
                    "latitude": "latitude",
                    "longitude": "longitude",
                    "manageBy": "smc_agency",
                    "name": "site_name_en",
                    "type": "type_of_settlement"
                },
                "admins": {
                    "admin1": {
                        "pcode": "Admin1",
                        "name": "governorate"
                    },
                    "admin2": {
                        "pcode": "Admin2",
                        "name": "district"
                    },
                    "admin3": {
                        "pcode": "Admin3",
                        "name": "sub_district"
                    }
                }
            },
            "indicators": {
                "area": [
                    {
                        "type": "site_count"
                    },
                    {
                        "type": "people_count",
                        "entryCode": "nb_site_residents_ind"
                    },
                    {
                        "type": "standard",
                        "name": {
                            "en": "# Shelters",
                            "ar": "عدد المآوي في الموقع"
                        },
                        "entryCode": "nb_shelters",
                        "iconOchaName": "Shelter"
                    }
                ],
                "site": [
                    {
                        "type": "standard",
                        "name": {
                            "en": "Site Residents",
                            "ar": "ادخل إجمالي عدد سكان الموقع -  الأفراد"
                        },
                        "entryCode": "nb_site_residents_ind",
                        "iconOchaName": "People-affected"
                    },
                    {
                        "type": "standard",
                        "name": {
                            "en": "# Shelters",
                            "ar": "عدد المآوي في الموقع"
                        },
                        "entryCode": "nb_shelters",
                        "iconOchaName": "Shelter"
                    },
                    {
                        "type": "standard",
                        "name": {
                            "en": "# SMC Staff",
                            "ar": "العدد الكلي لموظفي إدارة وتنسيق الموقع"
                        },
                        "entryCode": "smc_total",
                        "iconOchaName": "Staff-management"
                    }
                ]
            }
        }
    ],
    "options": {
        "showDemoBanner": true,
        "keepThematicOrderFromFDF": true,
        "exportAsCSVonHomePage": true,
        "mapLegendDisplayStyle":"folded"
    }
}
